oceanlyz/__init__.py
oceanlyz/oceanlyz/PcorFFTFun.py
oceanlyz/oceanlyz/PcorZerocrossingFun.py
oceanlyz/oceanlyz/SeaSwellFun.py
oceanlyz/oceanlyz/WaveSpectraFun.py
oceanlyz/oceanlyz/WaveZerocrossingFun.py
oceanlyz/oceanlyz/__init__.py
oceanlyz/oceanlyz/oceanlyz.py
oceanlyz-2.0.dist-info/License.txt
oceanlyz-2.0.dist-info/METADATA
oceanlyz-2.0.dist-info/WHEEL
oceanlyz-2.0.dist-info/top_level.txt
oceanlyz-2.0.dist-info/RECORD
