Metadata-Version: 2.1
Name: oceanlyz
Version: 2.0
Summary: Ocean Wave Analyzing Toolbox
Home-page: http://www.arashkarimpour.com
Author: Arash Karimpour
Author-email: akarimp@g.clemson.edu
License: UNKNOWN
Platform: UNKNOWN
Classifier: Programming Language :: Python :: 3
Classifier: License :: OSI Approved :: MIT License
Classifier: Operating System :: OS Independent
Requires-Python: >=3.6
License-File: License.txt
Requires-Dist: numpy
Requires-Dist: scipy
Requires-Dist: matplotlib
